LICENSE.txt
MANIFEST.in
README.md
setup.cfg
setup.py
textualize/__init__.py
textualize/test_textualize.py
textualize/textualize.py
textualize.egg-info/PKG-INFO
textualize.egg-info/SOURCES.txt
textualize.egg-info/dependency_links.txt
textualize.egg-info/top_level.txt