Metadata-Version: 1.1
Name: textualize
Version: 0.1
Summary: Tool for textualizing integers.
Home-page: https://github.com/kefkius/textualize
Author: Tyler Willis
Author-email: kefkius@mail.com
License: UNKNOWN
Keywords: textualize
Platform: UNKNOWN
Classifier: Programming Language :: Python
Classifier: License :: OSI Approved :: MIT License
